agentic_test_framework/__init__.py
agentic_test_framework/__main__.py
agentic_test_framework/actions/__init__.py
agentic_test_framework/actions/base.py
agentic_test_framework/config/__init__.py
agentic_test_framework/config/env_setup.py
agentic_test_framework/executor/__init__.py
agentic_test_framework/executor/playwright_executor.py
agentic_test_framework/parser/__init__.py
agentic_test_framework/parser/atc_parser.py
agentic_test_framework/parser/atc_template.py
agentic_test_framework/parser/openai_parser.py
agentic_test_framework/reporter/__init__.py
agentic_test_framework/reporter/html_reporter.py
agentic_test_framework/runner/__init__.py
agentic_test_framework/runner/test_runner.py
agentic_test_framework-0.1.3.dist-info/licenses/LICENSE
agentic_test_framework-0.1.3.dist-info/METADATA
agentic_test_framework-0.1.3.dist-info/WHEEL
agentic_test_framework-0.1.3.dist-info/entry_points.txt
agentic_test_framework-0.1.3.dist-info/top_level.txt
agentic_test_framework-0.1.3.dist-info/RECORD
