Metadata-Version: 2.4
Name: agentic-test-framework
Version: 0.1.3
Summary: AI-powered browser testing framework using natural language and OpenAI
Author-email: "Dr. Fatih Tekin" <fatih.tekin.de@gmail.com>
License: MIT
Project-URL: Homepage, https://github.com/DrFatihTekin/agentic-test-framework/tree/master
Project-URL: Documentation, https://github.com/DrFatihTekin/agentic-test-framework/tree/master/README.md
Project-URL: Repository, https://github.com/DrFatihTekin/agentic-test-framework
Keywords: testing,automation,ai,playwright,openai,browser-testing
Classifier: Development Status :: 3 - Alpha
Classifier: Intended Audience :: Developers
Classifier: Topic :: Software Development :: Testing
Classifier: License :: OSI Approved :: MIT License
Classifier: Programming Language :: Python :: 3.11
Classifier: Programming Language :: Python :: 3.12
Requires-Python: >=3.11
License-File: LICENSE
Requires-Dist: playwright>=1.41.0
Requires-Dist: openai>=1.10.0
Requires-Dist: pydantic>=2.5.0
Requires-Dist: python-dotenv>=1.0.0
Requires-Dist: pyyaml>=6.0.0
Provides-Extra: dev
Requires-Dist: pytest>=7.4.0; extra == "dev"
Requires-Dist: pytest-asyncio>=0.23.0; extra == "dev"
Dynamic: license-file
